README.rst
setup.cfg
setup.py
cdochain/__init__.py
cdochain/chaining.py
cdochain/exceptions.py
cdochain/helpers.py
cdochain.egg-info/PKG-INFO
cdochain.egg-info/SOURCES.txt
cdochain.egg-info/dependency_links.txt
cdochain.egg-info/not-zip-safe
cdochain.egg-info/requires.txt
cdochain.egg-info/top_level.txt