Metadata-Version: 1.1
Name: cdochain
Version: 0.2a73
Summary: Easy chaining of cdo methods.
Home-page: https://github.com/OnionNinja/cdochain
Author: Uğur Çayoğlu
Author-email: urcyglu@gmail.com
License: MIT
Keywords: netcdf,cdo,wrapper,chaining
Platform: UNKNOWN
Classifier: Development Status :: 3 - Alpha
Classifier: Intended Audience :: Science/Research
Classifier: Natural Language :: English
Classifier: Operating System :: POSIX :: Linux
Classifier: Programming Language :: Python :: 3 :: Only
Classifier: Topic :: Scientific/Engineering :: GIS
Classifier: Topic :: Scientific/Engineering :: Information Analysis
Classifier: Intended Audience :: Science/Research
